symphony_familiarity/__init__.py
symphony_familiarity/_frontend.py
symphony_familiarity/_version.py
symphony_familiarity/widget.py
symphony_familiarity/labextension/build_log.json
symphony_familiarity/labextension/package.json
symphony_familiarity/labextension/static/lib_index_js.6858ef5199d703b6e321.js
symphony_familiarity/labextension/static/lib_index_js.6858ef5199d703b6e321.js.map
symphony_familiarity/labextension/static/lib_index_js.8482c91a35944c1b58f3.js
symphony_familiarity/labextension/static/lib_index_js.8482c91a35944c1b58f3.js.map
symphony_familiarity/labextension/static/remoteEntry.81c52a395a7ce341e118.js
symphony_familiarity/labextension/static/remoteEntry.81c52a395a7ce341e118.js.map
symphony_familiarity/labextension/static/remoteEntry.9d20416c0797bfa36b90.js
symphony_familiarity/labextension/static/remoteEntry.9d20416c0797bfa36b90.js.map
symphony_familiarity/labextension/static/style.js
symphony_familiarity/nbextension/extension.js
symphony_familiarity/nbextension/index.js
symphony_familiarity/standalone/widgets/SymphonyFamiliarity.js
symphony_familiarity/standalone/widgets/SymphonyFamiliarity.js.map
symphony_familiarity-1.0.2.data/data/etc/jupyter/nbconfig/notebook.d/symphony_familiarity.json
symphony_familiarity-1.0.2.data/data/share/jupyter/labextensions/symphony-familiarity/build_log.json
symphony_familiarity-1.0.2.data/data/share/jupyter/labextensions/symphony-familiarity/install.json
symphony_familiarity-1.0.2.data/data/share/jupyter/labextensions/symphony-familiarity/package.json
symphony_familiarity-1.0.2.data/data/share/jupyter/labextensions/symphony-familiarity/static/lib_index_js.6858ef5199d703b6e321.js
symphony_familiarity-1.0.2.data/data/share/jupyter/labextensions/symphony-familiarity/static/lib_index_js.6858ef5199d703b6e321.js.map
symphony_familiarity-1.0.2.data/data/share/jupyter/labextensions/symphony-familiarity/static/remoteEntry.9d20416c0797bfa36b90.js
symphony_familiarity-1.0.2.dist-info/LICENSE.txt
symphony_familiarity-1.0.2.dist-info/METADATA
symphony_familiarity-1.0.2.dist-info/WHEEL
symphony_familiarity-1.0.2.dist-info/top_level.txt
symphony_familiarity-1.0.2.dist-info/RECORD
